{
  "eventId": "10",
  "data": [
    {
      "rank": 1,
      "score": 58111027,
      "userId": 7013930982571286000
    },
    {
      "rank": 2,
      "score": 33333333,
      "userId": 7014345925502098000
    },
    {
      "rank": 3,
      "score": 30000000,
      "userId": 7014120160122510000
    },
    {
      "rank": 4,
      "score": 21000111,
      "userId": 7013400152862088000
    },
    {
      "rank": 5,
      "score": 17171717,
      "userId": 7013400564893687000
    },
    {
      "rank": 6,
      "score": 17032591,
      "userId": 7015445868975414000
    },
    {
      "rank": 7,
      "score": 17000108,
      "userId": 7014401641814433000
    },
    {
      "rank": 8,
      "score": 16381027,
      "userId": 7013611844694810000
    },
    {
      "rank": 9,
      "score": 16356861,
      "userId": 7021074434027101000
    },
    {
      "rank": 10,
      "score": 16333333,
      "userId": 7014025541384936000
    },
    {
      "rank": 11,
      "score": 16259214,
      "userId": 7013556328048139000
    },
    {
      "rank": 12,
      "score": 14596680,
      "userId": 7017508827532631000
    },
    {
      "rank": 13,
      "score": 9666666,
      "userId": 7029599152057179000
    },
    {
      "rank": 14,
      "score": 9381427,
      "userId": 7021936323514883000
    },
    {
      "rank": 15,
      "score": 8756786,
      "userId": 7013411759663095000
    },
    {
      "rank": 16,
      "score": 8690180,
      "userId": 7020368507976162000
    },
    {
      "rank": 17,
      "score": 8620582,
      "userId": 7022286796994207000
    },
    {
      "rank": 18,
      "score": 8617279,
      "userId": 7013766761866878000
    },
    {
      "rank": 19,
      "score": 8418638,
      "userId": 7015498993690140000
    },
    {
      "rank": 20,
      "score": 8395275,
      "userId": 7022487868086148000
    },
    {
      "rank": 21,
      "score": 8393558,
      "userId": 7013705314147016000
    },
    {
      "rank": 22,
      "score": 8101578,
      "userId": 7013561911312883000
    },
    {
      "rank": 23,
      "score": 7028819,
      "userId": 7013504300005662000
    },
    {
      "rank": 24,
      "score": 6927786,
      "userId": 7015948990281948000
    },
    {
      "rank": 25,
      "score": 6422430,
      "userId": 7013396580405485000
    },
    {
      "rank": 26,
      "score": 6390356,
      "userId": 7047814333308444000
    },
    {
      "rank": 27,
      "score": 6310762,
      "userId": 7013969679437798000
    },
    {
      "rank": 28,
      "score": 6303188,
      "userId": 7018455908347010000
    },
    {
      "rank": 29,
      "score": 6264321,
      "userId": 7019898968192703000
    },
    {
      "rank": 30,
      "score": 6257530,
      "userId": 7017066499353550000
    },
    {
      "rank": 31,
      "score": 6196268,
      "userId": 7037054643582852000
    },
    {
      "rank": 32,
      "score": 6056352,
      "userId": 7013388994960530000
    },
    {
      "rank": 33,
      "score": 5876969,
      "userId": 7015620378580229000
    },
    {
      "rank": 34,
      "score": 5847442,
      "userId": 7016485549368237000
    },
    {
      "rank": 35,
      "score": 5725129,
      "userId": 7013610179644104000
    },
    {
      "rank": 36,
      "score": 5687397,
      "userId": 7018535998401453000
    },
    {
      "rank": 37,
      "score": 5653560,
      "userId": 7025904592902725000
    },
    {
      "rank": 38,
      "score": 5616705,
      "userId": 7013571100982697000
    },
    {
      "rank": 39,
      "score": 5581996,
      "userId": 7002488682666139000
    },
    {
      "rank": 40,
      "score": 5518012,
      "userId": 7026424108665806000
    },
    {
      "rank": 41,
      "score": 5496904,
      "userId": 7051121475125861000
    },
    {
      "rank": 42,
      "score": 5495062,
      "userId": 7043242628456144000
    },
    {
      "rank": 43,
      "score": 5455312,
      "userId": 7017451911242653000
    },
    {
      "rank": 44,
      "score": 5366430,
      "userId": 7024035262288141000
    },
    {
      "rank": 45,
      "score": 5313924,
      "userId": 7013644533908954000
    },
    {
      "rank": 46,
      "score": 5306045,
      "userId": 7050039078418537000
    },
    {
      "rank": 47,
      "score": 5244397,
      "userId": 7040730429883702000
    },
    {
      "rank": 48,
      "score": 5207381,
      "userId": 7019633186481167000
    },
    {
      "rank": 49,
      "score": 5178407,
      "userId": 7013536504672787000
    },
    {
      "rank": 50,
      "score": 5168178,
      "userId": 7030302034645638000
    },
    {
      "rank": 51,
      "score": 5086968,
      "userId": 7037764393085459000
    },
    {
      "rank": 52,
      "score": 4665800,
      "userId": 7018980478057258000
    },
    {
      "rank": 53,
      "score": 4606224,
      "userId": 7013527449409625000
    },
    {
      "rank": 54,
      "score": 4581633,
      "userId": 7013488602021813000
    },
    {
      "rank": 55,
      "score": 4407952,
      "userId": 7013423819234975000
    },
    {
      "rank": 56,
      "score": 4362962,
      "userId": 7017256729507552000
    },
    {
      "rank": 57,
      "score": 4326173,
      "userId": 7014685632060661000
    },
    {
      "rank": 58,
      "score": 4299052,
      "userId": 7013403093551570000
    },
    {
      "rank": 59,
      "score": 4290530,
      "userId": 7013485164638756000
    },
    {
      "rank": 60,
      "score": 4208397,
      "userId": 7013557685006147000
    },
    {
      "rank": 61,
      "score": 4093960,
      "userId": 7013548574407515000
    },
    {
      "rank": 62,
      "score": 4006883,
      "userId": 7021889242880237000
    },
    {
      "rank": 63,
      "score": 4001811,
      "userId": 7013611496076959000
    },
    {
      "rank": 64,
      "score": 4001811,
      "userId": 7015652919538163000
    },
    {
      "rank": 65,
      "score": 3989774,
      "userId": 7013492456155225000
    },
    {
      "rank": 66,
      "score": 3981900,
      "userId": 7013504596605804000
    },
    {
      "rank": 67,
      "score": 3939624,
      "userId": 7043807937848172000
    },
    {
      "rank": 68,
      "score": 3900200,
      "userId": 7041401854332247000
    },
    {
      "rank": 69,
      "score": 3890393,
      "userId": 7013502739288415000
    },
    {
      "rank": 70,
      "score": 3876813,
      "userId": 7013515330035228000
    },
    {
      "rank": 71,
      "score": 3876014,
      "userId": 7013566341818899000
    },
    {
      "rank": 72,
      "score": 3857672,
      "userId": 7013991627266186000
    },
    {
      "rank": 73,
      "score": 3844509,
      "userId": 7049334393017605000
    },
    {
      "rank": 74,
      "score": 3835022,
      "userId": 7013502198671744000
    },
    {
      "rank": 75,
      "score": 3833286,
      "userId": 7029547990071385000
    },
    {
      "rank": 76,
      "score": 3825716,
      "userId": 7014403958286360000
    },
    {
      "rank": 77,
      "score": 3821232,
      "userId": 7013681233301495000
    },
    {
      "rank": 78,
      "score": 3816350,
      "userId": 7016134403521027000
    },
    {
      "rank": 79,
      "score": 3810468,
      "userId": 7018819614234795000
    },
    {
      "rank": 80,
      "score": 3807435,
      "userId": 7013482963564338000
    },
    {
      "rank": 81,
      "score": 3805551,
      "userId": 7013509829117468000
    },
    {
      "rank": 82,
      "score": 3804376,
      "userId": 7013944285989150000
    },
    {
      "rank": 83,
      "score": 3799493,
      "userId": 7045134218015464000
    },
    {
      "rank": 84,
      "score": 3796985,
      "userId": 7017734546468740000
    },
    {
      "rank": 85,
      "score": 3786917,
      "userId": 7013386161129463000
    },
    {
      "rank": 86,
      "score": 3786676,
      "userId": 7002652987147656000
    },
    {
      "rank": 87,
      "score": 3786108,
      "userId": 7013842369166482000
    },
    {
      "rank": 88,
      "score": 3783888,
      "userId": 7013486244768538000
    },
    {
      "rank": 89,
      "score": 3779124,
      "userId": 7013728473793584000
    },
    {
      "rank": 90,
      "score": 3774277,
      "userId": 7013386429183057000
    },
    {
      "rank": 91,
      "score": 3764190,
      "userId": 7022513084812090000
    },
    {
      "rank": 92,
      "score": 3760776,
      "userId": 7018091021674520000
    },
    {
      "rank": 93,
      "score": 3754703,
      "userId": 7014118219275542000
    },
    {
      "rank": 94,
      "score": 3748495,
      "userId": 7014020401261239000
    },
    {
      "rank": 95,
      "score": 3741338,
      "userId": 7013358884962459000
    },
    {
      "rank": 96,
      "score": 3739997,
      "userId": 7013753824942792000
    },
    {
      "rank": 97,
      "score": 3737071,
      "userId": 7049861307188829000
    },
    {
      "rank": 98,
      "score": 3700918,
      "userId": 7015408946269789000
    },
    {
      "rank": 99,
      "score": 3684996,
      "userId": 7016775158862142000
    },
    {
      "rank": 100,
      "score": 3683243,
      "userId": 7018100469805440000
    },
    {
      "rank": 200,
      "score": 2324402,
      "userId": 7026943218461859000
    },
    {
      "rank": 300,
      "score": 2006106,
      "userId": 7013484084358077000
    },
    {
      "rank": 400,
      "score": 1871636,
      "userId": 7013475096052604000
    },
    {
      "rank": 500,
      "score": 1845276,
      "userId": 7014096159174139000
    },
    {
      "rank": 1000,
      "score": 1552257,
      "userId": 7031213630192410000
    },
    {
      "rank": 2000,
      "score": 1223909,
      "userId": 7014375737067249000
    },
    {
      "rank": 3000,
      "score": 1077238,
      "userId": 7014783508409474000
    },
    {
      "rank": 4000,
      "score": 983863,
      "userId": 7025479889205698000
    },
    {
      "rank": 5000,
      "score": 925208,
      "userId": 7021802142511980000
    },
    {
      "rank": 10000,
      "score": 615226,
      "userId": 7013387307055259000
    },
    {
      "rank": 20000,
      "score": 371711,
      "userId": 7016003172015545000
    },
    {
      "rank": 30000,
      "score": 267761,
      "userId": 7014030399647243000
    },
    {
      "rank": 40000,
      "score": 198076,
      "userId": 7014111328545660000
    },
    {
      "rank": 50000,
      "score": 140585,
      "userId": 7048433156499955000
    },
    {
      "rank": 100000,
      "score": 15525,
      "userId": 7013382862082858000
    }
  ]
}