{
  "eventId": "112",
  "characterId": 18,
  "data": [
    {
      "rank": 1,
      "score": 64300827,
      "userId": "7132512942364416770"
    },
    {
      "rank": 2,
      "score": 56301537,
      "userId": "7162765634542295810"
    },
    {
      "rank": 3,
      "score": 54523308,
      "userId": "7196196881788099329"
    },
    {
      "rank": 4,
      "score": 48035311,
      "userId": "7209099759267846913"
    },
    {
      "rank": 5,
      "score": 47413127,
      "userId": "7015202070395575041"
    },
    {
      "rank": 6,
      "score": 44807752,
      "userId": "7095015219709287170"
    },
    {
      "rank": 7,
      "score": 41937086,
      "userId": "7150894731533523713"
    },
    {
      "rank": 8,
      "score": 40804937,
      "userId": "7013412485147532033"
    },
    {
      "rank": 9,
      "score": 40052127,
      "userId": "7168076249993173761"
    },
    {
      "rank": 10,
      "score": 39531967,
      "userId": "7316979540595612418"
    },
    {
      "rank": 11,
      "score": 37430127,
      "userId": "7013406207834692354"
    },
    {
      "rank": 12,
      "score": 32897865,
      "userId": "7103341406315469569"
    },
    {
      "rank": 13,
      "score": 30130127,
      "userId": "7002798502673816321"
    },
    {
      "rank": 14,
      "score": 28915621,
      "userId": "7013747024751385346"
    },
    {
      "rank": 15,
      "score": 28430127,
      "userId": "7059971202810403586"
    },
    {
      "rank": 16,
      "score": 28165203,
      "userId": "7055485601742756609"
    },
    {
      "rank": 17,
      "score": 28126672,
      "userId": "7284449212807338753"
    },
    {
      "rank": 18,
      "score": 28120127,
      "userId": "7013418031640779521"
    },
    {
      "rank": 19,
      "score": 28000557,
      "userId": "7048195622108846850"
    },
    {
      "rank": 20,
      "score": 27777127,
      "userId": "7014449352399936257"
    },
    {
      "rank": 21,
      "score": 27675627,
      "userId": "7013753716360928001"
    },
    {
      "rank": 22,
      "score": 27600127,
      "userId": "7135733431388117761"
    },
    {
      "rank": 23,
      "score": 27549298,
      "userId": "7262001968556579585"
    },
    {
      "rank": 24,
      "score": 27254022,
      "userId": "7185152334421302017"
    },
    {
      "rank": 25,
      "score": 27210127,
      "userId": "7013598607794330369"
    },
    {
      "rank": 26,
      "score": 27017553,
      "userId": "7045614833840020225"
    },
    {
      "rank": 27,
      "score": 27010127,
      "userId": "7367341861654272785"
    },
    {
      "rank": 28,
      "score": 27010127,
      "userId": "7043704764474907393"
    },
    {
      "rank": 29,
      "score": 27010127,
      "userId": "7071171477395168001"
    },
    {
      "rank": 30,
      "score": 27000127,
      "userId": "7244574283090320129"
    },
    {
      "rank": 31,
      "score": 27000127,
      "userId": "7067859704914926338"
    },
    {
      "rank": 32,
      "score": 27000127,
      "userId": "7015512084205034242"
    },
    {
      "rank": 33,
      "score": 27000127,
      "userId": "7357175626799078160"
    },
    {
      "rank": 34,
      "score": 27000127,
      "userId": "7107249644991945474"
    },
    {
      "rank": 35,
      "score": 27000000,
      "userId": "7013667911336319746"
    },
    {
      "rank": 36,
      "score": 26451892,
      "userId": "7397584486042524417"
    },
    {
      "rank": 37,
      "score": 26319885,
      "userId": "7013478360382790401"
    },
    {
      "rank": 38,
      "score": 26060127,
      "userId": "7050694025480788737"
    },
    {
      "rank": 39,
      "score": 26022184,
      "userId": "7015219493802924802"
    },
    {
      "rank": 40,
      "score": 25957549,
      "userId": "7018025534747597570"
    },
    {
      "rank": 41,
      "score": 25922376,
      "userId": "7085115715417758465"
    },
    {
      "rank": 42,
      "score": 25865933,
      "userId": "7014672376801696513"
    },
    {
      "rank": 43,
      "score": 25827105,
      "userId": "7284664284716686081"
    },
    {
      "rank": 44,
      "score": 25770066,
      "userId": "7013445837833394946"
    },
    {
      "rank": 45,
      "score": 25699618,
      "userId": "7112877308196985602"
    },
    {
      "rank": 46,
      "score": 25601893,
      "userId": "7059385084109003522"
    },
    {
      "rank": 47,
      "score": 25568772,
      "userId": "7300588616198265601"
    },
    {
      "rank": 48,
      "score": 25555127,
      "userId": "7217069666265635586"
    },
    {
      "rank": 49,
      "score": 25530831,
      "userId": "7021404115238509314"
    },
    {
      "rank": 50,
      "score": 25520127,
      "userId": "7013746376555174658"
    },
    {
      "rank": 51,
      "score": 25508261,
      "userId": "7019922050907380482"
    },
    {
      "rank": 52,
      "score": 25504973,
      "userId": "7014712058025417474"
    },
    {
      "rank": 53,
      "score": 25504035,
      "userId": "7109697180075629313"
    },
    {
      "rank": 54,
      "score": 25459441,
      "userId": "7182857767055809281"
    },
    {
      "rank": 55,
      "score": 25430127,
      "userId": "7013386145153456897"
    },
    {
      "rank": 56,
      "score": 25288803,
      "userId": "7028214397352893185"
    },
    {
      "rank": 57,
      "score": 25245235,
      "userId": "7118751480185871106"
    },
    {
      "rank": 58,
      "score": 25233780,
      "userId": "7002910339612580610"
    },
    {
      "rank": 59,
      "score": 25215674,
      "userId": "7053440693125274370"
    },
    {
      "rank": 60,
      "score": 25207379,
      "userId": "7356216723428612881"
    },
    {
      "rank": 61,
      "score": 25199830,
      "userId": "7032108437123373825"
    },
    {
      "rank": 62,
      "score": 25197496,
      "userId": "7042538755244333826"
    },
    {
      "rank": 63,
      "score": 25175757,
      "userId": "7116018512187071233"
    },
    {
      "rank": 64,
      "score": 25165734,
      "userId": "7107155515876203265"
    },
    {
      "rank": 65,
      "score": 25154594,
      "userId": "7185832655429081857"
    },
    {
      "rank": 66,
      "score": 25127827,
      "userId": "7018410921332759298"
    },
    {
      "rank": 67,
      "score": 25127430,
      "userId": "7013982274026838785"
    },
    {
      "rank": 68,
      "score": 25127430,
      "userId": "7013403032125725442"
    },
    {
      "rank": 69,
      "score": 25127430,
      "userId": "7262324718815042305"
    },
    {
      "rank": 70,
      "score": 25108127,
      "userId": "7149928138213202690"
    },
    {
      "rank": 71,
      "score": 25084450,
      "userId": "7013400152862087937"
    },
    {
      "rank": 72,
      "score": 25065345,
      "userId": "7257123531333393153"
    },
    {
      "rank": 73,
      "score": 25050127,
      "userId": "7160912744018139905"
    },
    {
      "rank": 74,
      "score": 25046446,
      "userId": "7013559733365840642"
    },
    {
      "rank": 75,
      "score": 25029332,
      "userId": "7192984406833830658"
    },
    {
      "rank": 76,
      "score": 25028469,
      "userId": "7226795414937230082"
    },
    {
      "rank": 77,
      "score": 25021156,
      "userId": "7002440103637605121"
    },
    {
      "rank": 78,
      "score": 25017655,
      "userId": "7063292216202173186"
    },
    {
      "rank": 79,
      "score": 25013906,
      "userId": "7151136511466199809"
    },
    {
      "rank": 80,
      "score": 25000943,
      "userId": "7085312306921626370"
    },
    {
      "rank": 81,
      "score": 25000438,
      "userId": "7273904997585361665"
    },
    {
      "rank": 82,
      "score": 25000430,
      "userId": "7013751278136204033"
    },
    {
      "rank": 83,
      "score": 25000127,
      "userId": "7082959206411885314"
    },
    {
      "rank": 84,
      "score": 25000127,
      "userId": "7310547846095231745"
    },
    {
      "rank": 85,
      "score": 25000127,
      "userId": "7359592058870307601"
    },
    {
      "rank": 86,
      "score": 25000127,
      "userId": "7251022340883176193"
    },
    {
      "rank": 87,
      "score": 24967089,
      "userId": "7218138587945261826"
    },
    {
      "rank": 88,
      "score": 24959206,
      "userId": "7160716813146331905"
    },
    {
      "rank": 89,
      "score": 24942504,
      "userId": "7013556197534194433"
    },
    {
      "rank": 90,
      "score": 24889348,
      "userId": "7015574383448185602"
    },
    {
      "rank": 91,
      "score": 24872590,
      "userId": "7313568512386145025"
    },
    {
      "rank": 92,
      "score": 24844762,
      "userId": "7017389028291091202"
    },
    {
      "rank": 93,
      "score": 24805495,
      "userId": "7025903359626484482"
    },
    {
      "rank": 94,
      "score": 24787505,
      "userId": "7158838863102909185"
    },
    {
      "rank": 95,
      "score": 24760803,
      "userId": "7013431885988911874"
    },
    {
      "rank": 96,
      "score": 24751349,
      "userId": "7298937182360738562"
    },
    {
      "rank": 97,
      "score": 24742954,
      "userId": "7243630533023013634"
    },
    {
      "rank": 98,
      "score": 24683708,
      "userId": "7115968529337309954"
    },
    {
      "rank": 99,
      "score": 24668908,
      "userId": "7072353563011472130"
    },
    {
      "rank": 100,
      "score": 24616735,
      "userId": "7328651288839789314"
    }
  ]
}