{
  "eventId": "118",
  "characterId": 10,
  "data": [
    {
      "rank": 1,
      "score": 129826618,
      "userId": "7072282261126961921"
    },
    {
      "rank": 2,
      "score": 98251773,
      "userId": "7017416086907869953"
    },
    {
      "rank": 3,
      "score": 95234777,
      "userId": "7111561134918064898"
    },
    {
      "rank": 4,
      "score": 57302726,
      "userId": "7034224758191561473"
    },
    {
      "rank": 5,
      "score": 52000726,
      "userId": "7302230685912259330"
    },
    {
      "rank": 6,
      "score": 43593726,
      "userId": "7053204089626303233"
    },
    {
      "rank": 7,
      "score": 40702266,
      "userId": "7058645036090596097"
    },
    {
      "rank": 8,
      "score": 35911736,
      "userId": "7022278560979196674"
    },
    {
      "rank": 9,
      "score": 35888423,
      "userId": "7002733928016648962"
    },
    {
      "rank": 10,
      "score": 34000726,
      "userId": "7013786409916046082"
    },
    {
      "rank": 11,
      "score": 28835978,
      "userId": "7228107173103115010"
    },
    {
      "rank": 12,
      "score": 27424288,
      "userId": "7330462935799618305"
    },
    {
      "rank": 13,
      "score": 25969643,
      "userId": "7040796771823590145"
    },
    {
      "rank": 14,
      "score": 25525255,
      "userId": "7068636360252349185"
    },
    {
      "rank": 15,
      "score": 25110726,
      "userId": "7338405817697327873"
    },
    {
      "rank": 16,
      "score": 22000209,
      "userId": "7015263917312367361"
    },
    {
      "rank": 17,
      "score": 21651477,
      "userId": "7250736634398808833"
    },
    {
      "rank": 18,
      "score": 20760830,
      "userId": "7179660690607577858"
    },
    {
      "rank": 19,
      "score": 20726000,
      "userId": "7018924966578281217"
    },
    {
      "rank": 20,
      "score": 20520726,
      "userId": "7026402420527848193"
    },
    {
      "rank": 21,
      "score": 18822936,
      "userId": "7240745755386977026"
    },
    {
      "rank": 22,
      "score": 18545346,
      "userId": "7187754275177749249"
    },
    {
      "rank": 23,
      "score": 17260726,
      "userId": "7066067314432842498"
    },
    {
      "rank": 24,
      "score": 17006574,
      "userId": "7187677102316198658"
    },
    {
      "rank": 25,
      "score": 16520726,
      "userId": "7016040142313921281"
    },
    {
      "rank": 26,
      "score": 16477123,
      "userId": "7318744110330862338"
    },
    {
      "rank": 27,
      "score": 16381187,
      "userId": "7250282003541678849"
    },
    {
      "rank": 28,
      "score": 16050212,
      "userId": "7002538660105116417"
    },
    {
      "rank": 29,
      "score": 16000726,
      "userId": "7017309228943710977"
    },
    {
      "rank": 30,
      "score": 15927942,
      "userId": "7013692629544262401"
    },
    {
      "rank": 31,
      "score": 15915822,
      "userId": "7017038194923526913"
    },
    {
      "rank": 32,
      "score": 15583227,
      "userId": "7319028398083513089"
    },
    {
      "rank": 33,
      "score": 15304686,
      "userId": "7053882422773144322"
    },
    {
      "rank": 34,
      "score": 15272600,
      "userId": "7029683658726333186"
    },
    {
      "rank": 35,
      "score": 15201197,
      "userId": "7013561061617998594"
    },
    {
      "rank": 36,
      "score": 15200726,
      "userId": "7183664847576619777"
    },
    {
      "rank": 37,
      "score": 15166528,
      "userId": "7020743325292567298"
    },
    {
      "rank": 38,
      "score": 15022533,
      "userId": "7330333728897587969"
    },
    {
      "rank": 39,
      "score": 14869595,
      "userId": "7385775921560591105"
    },
    {
      "rank": 40,
      "score": 14670726,
      "userId": "7013682575009012481"
    },
    {
      "rank": 41,
      "score": 14555790,
      "userId": "7321792217167944450"
    },
    {
      "rank": 42,
      "score": 14555726,
      "userId": "7050808719034211073"
    },
    {
      "rank": 43,
      "score": 14303037,
      "userId": "7171754596678015745"
    },
    {
      "rank": 44,
      "score": 14265793,
      "userId": "7333497260971563777"
    },
    {
      "rank": 45,
      "score": 14138006,
      "userId": "7015630136917940994"
    },
    {
      "rank": 46,
      "score": 13948585,
      "userId": "7063064618897283842"
    },
    {
      "rank": 47,
      "score": 13914214,
      "userId": "7398013394663922448"
    },
    {
      "rank": 48,
      "score": 13830285,
      "userId": "7269363069506296577"
    },
    {
      "rank": 49,
      "score": 13785843,
      "userId": "7104671667594550018"
    },
    {
      "rank": 50,
      "score": 13738838,
      "userId": "7045915732349131521"
    },
    {
      "rank": 51,
      "score": 13613842,
      "userId": "7221807761196260098"
    },
    {
      "rank": 52,
      "score": 13552726,
      "userId": "7090430557900937985"
    },
    {
      "rank": 53,
      "score": 13494899,
      "userId": "7013593888677960450"
    },
    {
      "rank": 54,
      "score": 13488646,
      "userId": "7013691841828870914"
    },
    {
      "rank": 55,
      "score": 13299726,
      "userId": "7086750021160442625"
    },
    {
      "rank": 56,
      "score": 13299726,
      "userId": "7037026450565831425"
    },
    {
      "rank": 57,
      "score": 13185837,
      "userId": "7300074846535441153"
    },
    {
      "rank": 58,
      "score": 13149726,
      "userId": "7066462005271780097"
    },
    {
      "rank": 59,
      "score": 13144408,
      "userId": "7226019143945001729"
    },
    {
      "rank": 60,
      "score": 13110341,
      "userId": "7058254329521888001"
    },
    {
      "rank": 61,
      "score": 13087426,
      "userId": "7042954503670356737"
    },
    {
      "rank": 62,
      "score": 13000726,
      "userId": "7034079431232658178"
    },
    {
      "rank": 63,
      "score": 13000726,
      "userId": "7090528553812679426"
    },
    {
      "rank": 64,
      "score": 12761880,
      "userId": "7108905973645040385"
    },
    {
      "rank": 65,
      "score": 12679141,
      "userId": "7426595353157327672"
    },
    {
      "rank": 66,
      "score": 12673726,
      "userId": "7031480679070178049"
    },
    {
      "rank": 67,
      "score": 12672703,
      "userId": "7023738619454069505"
    },
    {
      "rank": 68,
      "score": 12612539,
      "userId": "7385715831675558672"
    },
    {
      "rank": 69,
      "score": 12520726,
      "userId": "7013511661659167489"
    },
    {
      "rank": 70,
      "score": 12499588,
      "userId": "7074912251874007809"
    },
    {
      "rank": 71,
      "score": 12430489,
      "userId": "7029310421429541634"
    },
    {
      "rank": 72,
      "score": 12416022,
      "userId": "7266678058986429186"
    },
    {
      "rank": 73,
      "score": 12407260,
      "userId": "7252721998051285762"
    },
    {
      "rank": 74,
      "score": 12382500,
      "userId": "7250455024185170690"
    },
    {
      "rank": 75,
      "score": 12350479,
      "userId": "7036266540584508161"
    },
    {
      "rank": 76,
      "score": 12340480,
      "userId": "7193295474999417601"
    },
    {
      "rank": 77,
      "score": 12309208,
      "userId": "7013686594423118593"
    },
    {
      "rank": 78,
      "score": 12272711,
      "userId": "7013547122905651969"
    },
    {
      "rank": 79,
      "score": 12271224,
      "userId": "7300454421308119809"
    },
    {
      "rank": 80,
      "score": 12260755,
      "userId": "7013510110563539713"
    },
    {
      "rank": 81,
      "score": 12242449,
      "userId": "7072046265265183490"
    },
    {
      "rank": 82,
      "score": 12174746,
      "userId": "7062322841256991490"
    },
    {
      "rank": 83,
      "score": 12172128,
      "userId": "7221608767220226817"
    },
    {
      "rank": 84,
      "score": 12160487,
      "userId": "7013590716077054722"
    },
    {
      "rank": 85,
      "score": 12135489,
      "userId": "7014295853057891074"
    },
    {
      "rank": 86,
      "score": 12135122,
      "userId": "7017643679808609026"
    },
    {
      "rank": 87,
      "score": 12133385,
      "userId": "7114586241080990465"
    },
    {
      "rank": 88,
      "score": 12110358,
      "userId": "7337603641659972353"
    },
    {
      "rank": 89,
      "score": 12102717,
      "userId": "7013539329200970498"
    },
    {
      "rank": 90,
      "score": 12073246,
      "userId": "7013701430922107649"
    },
    {
      "rank": 91,
      "score": 12062726,
      "userId": "7015502420457298690"
    },
    {
      "rank": 92,
      "score": 12034509,
      "userId": "7373161007008619281"
    },
    {
      "rank": 93,
      "score": 12025853,
      "userId": "7145053017686104833"
    },
    {
      "rank": 94,
      "score": 12011122,
      "userId": "7337900729455385346"
    },
    {
      "rank": 95,
      "score": 12009449,
      "userId": "7211097553197128450"
    },
    {
      "rank": 96,
      "score": 11998630,
      "userId": "7058571021565287170"
    },
    {
      "rank": 97,
      "score": 11998569,
      "userId": "7013667718524197633"
    },
    {
      "rank": 98,
      "score": 11992943,
      "userId": "7015545525038701314"
    },
    {
      "rank": 99,
      "score": 11978533,
      "userId": "7182023268528904961"
    },
    {
      "rank": 100,
      "score": 11962692,
      "userId": "7059991352586853122"
    }
  ]
}