{
  "eventId": "57",
  "data": [
    {
      "rank": 1,
      "score": 152001005,
      "userId": 7013662033845706000
    },
    {
      "rank": 2,
      "score": 141401005,
      "userId": 7013684688401276000
    },
    {
      "rank": 3,
      "score": 90001005,
      "userId": 7013390332377243000
    },
    {
      "rank": 4,
      "score": 73424208,
      "userId": 7089713326917459000
    },
    {
      "rank": 5,
      "score": 70001005,
      "userId": 7101286516974018000
    },
    {
      "rank": 6,
      "score": 67500000,
      "userId": 7058605332469325000
    },
    {
      "rank": 7,
      "score": 67000544,
      "userId": 7020419884417031000
    },
    {
      "rank": 8,
      "score": 66831005,
      "userId": 7013386814106918000
    },
    {
      "rank": 9,
      "score": 66801005,
      "userId": 7081677946485906000
    },
    {
      "rank": 10,
      "score": 66666442,
      "userId": 7028390346279230000
    },
    {
      "rank": 11,
      "score": 65683512,
      "userId": 7028168539911724000
    },
    {
      "rank": 12,
      "score": 31323012,
      "userId": 7037461745648131000
    },
    {
      "rank": 13,
      "score": 30767247,
      "userId": 7013601922112577000
    },
    {
      "rank": 14,
      "score": 28835552,
      "userId": 7017455902479539000
    },
    {
      "rank": 15,
      "score": 28609806,
      "userId": 7090151883003764000
    },
    {
      "rank": 16,
      "score": 28482646,
      "userId": 7013555373365812000
    },
    {
      "rank": 17,
      "score": 28111850,
      "userId": 7192068537584999000
    },
    {
      "rank": 18,
      "score": 28015205,
      "userId": 7154609029174533000
    },
    {
      "rank": 19,
      "score": 28015205,
      "userId": 7092091503916490000
    },
    {
      "rank": 20,
      "score": 27777497,
      "userId": 7013609355526299000
    },
    {
      "rank": 21,
      "score": 27168929,
      "userId": 7127104141981343000
    },
    {
      "rank": 22,
      "score": 25591262,
      "userId": 7013731695056739000
    },
    {
      "rank": 23,
      "score": 23521699,
      "userId": 7022456706818956000
    },
    {
      "rank": 24,
      "score": 21611085,
      "userId": 7209231200504880000
    },
    {
      "rank": 25,
      "score": 21225842,
      "userId": 7135597167883967000
    },
    {
      "rank": 26,
      "score": 21152000,
      "userId": 7059336990860320000
    },
    {
      "rank": 27,
      "score": 21114224,
      "userId": 7100509673245416000
    },
    {
      "rank": 28,
      "score": 21076397,
      "userId": 7116192111153733000
    },
    {
      "rank": 29,
      "score": 20195704,
      "userId": 7013389522637430000
    },
    {
      "rank": 30,
      "score": 20071227,
      "userId": 7002434068658953000
    },
    {
      "rank": 31,
      "score": 19952481,
      "userId": 7013485660568952000
    },
    {
      "rank": 32,
      "score": 19853894,
      "userId": 7030289257277267000
    },
    {
      "rank": 33,
      "score": 19313995,
      "userId": 7013385413167619000
    },
    {
      "rank": 34,
      "score": 18133775,
      "userId": 7013622526618377000
    },
    {
      "rank": 35,
      "score": 18096435,
      "userId": 7048041784328347000
    },
    {
      "rank": 36,
      "score": 18010056,
      "userId": 7100650852880522000
    },
    {
      "rank": 37,
      "score": 17936061,
      "userId": 7047771258133683000
    },
    {
      "rank": 38,
      "score": 17821227,
      "userId": 7013400447146794000
    },
    {
      "rank": 39,
      "score": 17520414,
      "userId": 7079474354362359000
    },
    {
      "rank": 40,
      "score": 17502231,
      "userId": 7002449981558889000
    },
    {
      "rank": 41,
      "score": 17261005,
      "userId": 7034079431232658000
    },
    {
      "rank": 42,
      "score": 16862397,
      "userId": 7013407299293453000
    },
    {
      "rank": 43,
      "score": 16801680,
      "userId": 7013668010108116000
    },
    {
      "rank": 44,
      "score": 16801563,
      "userId": 7074069482670595000
    },
    {
      "rank": 45,
      "score": 16800430,
      "userId": 7029991253777587000
    },
    {
      "rank": 46,
      "score": 16620254,
      "userId": 7082614568450678000
    },
    {
      "rank": 47,
      "score": 16597178,
      "userId": 7013386693554363000
    },
    {
      "rank": 48,
      "score": 16595008,
      "userId": 7182862686055636000
    },
    {
      "rank": 49,
      "score": 16406495,
      "userId": 7059222754897386000
    },
    {
      "rank": 50,
      "score": 16318677,
      "userId": 7081521178417896000
    },
    {
      "rank": 51,
      "score": 16002419,
      "userId": 7015849916400688000
    },
    {
      "rank": 52,
      "score": 15043075,
      "userId": 7013399507610148000
    },
    {
      "rank": 53,
      "score": 14555982,
      "userId": 7014740236429254000
    },
    {
      "rank": 54,
      "score": 14431072,
      "userId": 7037726107864440000
    },
    {
      "rank": 55,
      "score": 13807040,
      "userId": 7075574801825340000
    },
    {
      "rank": 56,
      "score": 11706040,
      "userId": 7123394380551036000
    },
    {
      "rank": 57,
      "score": 11544449,
      "userId": 7035593514289225000
    },
    {
      "rank": 58,
      "score": 11521005,
      "userId": 7027495355470061000
    },
    {
      "rank": 59,
      "score": 11506611,
      "userId": 7101268179187523000
    },
    {
      "rank": 60,
      "score": 11394078,
      "userId": 7013545876249517000
    },
    {
      "rank": 61,
      "score": 11015083,
      "userId": 7120203722692681000
    },
    {
      "rank": 62,
      "score": 10726097,
      "userId": 7014669453749247000
    },
    {
      "rank": 63,
      "score": 10599806,
      "userId": 7014823217001160000
    },
    {
      "rank": 64,
      "score": 10592343,
      "userId": 7102800381905952000
    },
    {
      "rank": 65,
      "score": 10583220,
      "userId": 7161085583476350000
    },
    {
      "rank": 66,
      "score": 10563659,
      "userId": 7053394058315701000
    },
    {
      "rank": 67,
      "score": 10462341,
      "userId": 7081267082670677000
    },
    {
      "rank": 68,
      "score": 10422709,
      "userId": 7061342849786240000
    },
    {
      "rank": 69,
      "score": 10403899,
      "userId": 7014451138661555000
    },
    {
      "rank": 70,
      "score": 10354408,
      "userId": 7049111709117652000
    },
    {
      "rank": 71,
      "score": 10330534,
      "userId": 7214550820795276000
    },
    {
      "rank": 72,
      "score": 10270210,
      "userId": 7014035868851822000
    },
    {
      "rank": 73,
      "score": 10258526,
      "userId": 7110763617842421000
    },
    {
      "rank": 74,
      "score": 10230533,
      "userId": 7185926247518625000
    },
    {
      "rank": 75,
      "score": 10203987,
      "userId": 7013387609875504000
    },
    {
      "rank": 76,
      "score": 10169619,
      "userId": 7039930789517286000
    },
    {
      "rank": 77,
      "score": 10115947,
      "userId": 7111323774452096000
    },
    {
      "rank": 78,
      "score": 10097158,
      "userId": 7002451386986208000
    },
    {
      "rank": 79,
      "score": 10091024,
      "userId": 7013749934755323000
    },
    {
      "rank": 80,
      "score": 10080377,
      "userId": 7015974469726428000
    },
    {
      "rank": 81,
      "score": 10078975,
      "userId": 7016348828957728000
    },
    {
      "rank": 82,
      "score": 10061085,
      "userId": 7013611678927478000
    },
    {
      "rank": 83,
      "score": 10055536,
      "userId": 7013673408185720000
    },
    {
      "rank": 84,
      "score": 10051210,
      "userId": 7013704050076261000
    },
    {
      "rank": 85,
      "score": 10051206,
      "userId": 7016595943684349000
    },
    {
      "rank": 86,
      "score": 10051152,
      "userId": 7013644533908954000
    },
    {
      "rank": 87,
      "score": 10050414,
      "userId": 7099370251963391000
    },
    {
      "rank": 88,
      "score": 10031382,
      "userId": 7219901822796897000
    },
    {
      "rank": 89,
      "score": 10013767,
      "userId": 7059361615917096000
    },
    {
      "rank": 90,
      "score": 10003802,
      "userId": 7146802515009461000
    },
    {
      "rank": 91,
      "score": 10001344,
      "userId": 7013541074098773000
    },
    {
      "rank": 92,
      "score": 10001050,
      "userId": 7049956993133518000
    },
    {
      "rank": 93,
      "score": 9999165,
      "userId": 7049191463011376000
    },
    {
      "rank": 94,
      "score": 9998767,
      "userId": 7013590501123399000
    },
    {
      "rank": 95,
      "score": 9991941,
      "userId": 7013662297616834000
    },
    {
      "rank": 96,
      "score": 9987802,
      "userId": 7069818422472793000
    },
    {
      "rank": 97,
      "score": 9976772,
      "userId": 7021404115238510000
    },
    {
      "rank": 98,
      "score": 9957243,
      "userId": 7030766826640580000
    },
    {
      "rank": 99,
      "score": 9948958,
      "userId": 7120422853639462000
    },
    {
      "rank": 100,
      "score": 9883514,
      "userId": 7013594871944650000
    },
    {
      "rank": 200,
      "score": 4974986,
      "userId": 7113039496069045000
    },
    {
      "rank": 300,
      "score": 4251592,
      "userId": 7013677669120433000
    },
    {
      "rank": 400,
      "score": 4049748,
      "userId": 7162504471438794000
    },
    {
      "rank": 500,
      "score": 3995897,
      "userId": 7029626460465815000
    },
    {
      "rank": 1000,
      "score": 3234955,
      "userId": 7134215155646406000
    },
    {
      "rank": 2000,
      "score": 2288978,
      "userId": 7210085262758796000
    },
    {
      "rank": 3000,
      "score": 1906111,
      "userId": 7185048277933465000
    },
    {
      "rank": 4000,
      "score": 1671910,
      "userId": 7015955082546257000
    },
    {
      "rank": 5000,
      "score": 1542701,
      "userId": 7027866891901443000
    },
    {
      "rank": 10000,
      "score": 885399,
      "userId": 7013381175771291000
    },
    {
      "rank": 20000,
      "score": 462075,
      "userId": 7109829191327194000
    },
    {
      "rank": 30000,
      "score": 307379,
      "userId": 7164791436284616000
    },
    {
      "rank": 40000,
      "score": 219255,
      "userId": 7163836102233628000
    },
    {
      "rank": 50000,
      "score": 160338,
      "userId": 7043028546012601000
    },
    {
      "rank": 100000,
      "score": 31965,
      "userId": 7013648863521234000
    }
  ]
}