{
  "eventId": "86",
  "data": [
    {
      "rank": 1,
      "score": 222211302,
      "userId": "7013390207038806786"
    },
    {
      "rank": 2,
      "score": 200796301,
      "userId": "7027543929075571457"
    },
    {
      "rank": 3,
      "score": 130000302,
      "userId": "7109243147145861889"
    },
    {
      "rank": 4,
      "score": 103020921,
      "userId": "7081213679076694786"
    },
    {
      "rank": 5,
      "score": 39200300,
      "userId": "7014047579868650241"
    },
    {
      "rank": 6,
      "score": 39050302,
      "userId": "7013868053528271617"
    },
    {
      "rank": 7,
      "score": 38030302,
      "userId": "7239955342485084929"
    },
    {
      "rank": 8,
      "score": 38000302,
      "userId": "7014376493736418050"
    },
    {
      "rank": 9,
      "score": 37777302,
      "userId": "7017129271399586562"
    },
    {
      "rank": 10,
      "score": 36520302,
      "userId": "7034224758191561473"
    },
    {
      "rank": 11,
      "score": 33520302,
      "userId": "7290916982944340737"
    },
    {
      "rank": 12,
      "score": 33070858,
      "userId": "7042569550168283906"
    },
    {
      "rank": 13,
      "score": 31763525,
      "userId": "7013688598545488642"
    },
    {
      "rank": 14,
      "score": 30775412,
      "userId": "7171413144403843841"
    },
    {
      "rank": 15,
      "score": 30414302,
      "userId": "7079820188442516225"
    },
    {
      "rank": 16,
      "score": 30200302,
      "userId": "7013715748904295169"
    },
    {
      "rank": 17,
      "score": 30020302,
      "userId": "7285383433793280769"
    },
    {
      "rank": 18,
      "score": 29989071,
      "userId": "7077450902524779265"
    },
    {
      "rank": 19,
      "score": 29395805,
      "userId": "7044009609136413441"
    },
    {
      "rank": 20,
      "score": 29294420,
      "userId": "7013593888677960450"
    },
    {
      "rank": 21,
      "score": 27666278,
      "userId": "7095537209096313601"
    },
    {
      "rank": 22,
      "score": 23650456,
      "userId": "7328475420607699714"
    },
    {
      "rank": 23,
      "score": 21120302,
      "userId": "7253095450574625538"
    },
    {
      "rank": 24,
      "score": 21091302,
      "userId": "7022406862817712898"
    },
    {
      "rank": 25,
      "score": 20220410,
      "userId": "7022423624477055746"
    },
    {
      "rank": 26,
      "score": 19999985,
      "userId": "7126843935569353473"
    },
    {
      "rank": 27,
      "score": 19846999,
      "userId": "7183284048452770562"
    },
    {
      "rank": 28,
      "score": 19704956,
      "userId": "7092687874012781313"
    },
    {
      "rank": 29,
      "score": 17260302,
      "userId": "7019565380394048257"
    },
    {
      "rank": 30,
      "score": 16680726,
      "userId": "7024540355941079809"
    },
    {
      "rank": 31,
      "score": 15565982,
      "userId": "7013391903563586305"
    },
    {
      "rank": 32,
      "score": 14626502,
      "userId": "7194781325893688066"
    },
    {
      "rank": 33,
      "score": 13520831,
      "userId": "7017294331899812609"
    },
    {
      "rank": 34,
      "score": 13064602,
      "userId": "7132806075690015489"
    },
    {
      "rank": 35,
      "score": 13011530,
      "userId": "7058254653418429185"
    },
    {
      "rank": 36,
      "score": 12993313,
      "userId": "7045826536015977217"
    },
    {
      "rank": 37,
      "score": 12924896,
      "userId": "7029938909232618241"
    },
    {
      "rank": 38,
      "score": 12660302,
      "userId": "7209919416455338753"
    },
    {
      "rank": 39,
      "score": 12542605,
      "userId": "7260025999750945537"
    },
    {
      "rank": 40,
      "score": 12536854,
      "userId": "7274208446273035010"
    },
    {
      "rank": 41,
      "score": 12375813,
      "userId": "7014649856723606273"
    },
    {
      "rank": 42,
      "score": 12265122,
      "userId": "7013730112495721217"
    },
    {
      "rank": 43,
      "score": 12005143,
      "userId": "7013710818105858817"
    },
    {
      "rank": 44,
      "score": 11862454,
      "userId": "7325024926518336258"
    },
    {
      "rank": 45,
      "score": 11745842,
      "userId": "7053204089626303233"
    },
    {
      "rank": 46,
      "score": 11671870,
      "userId": "7130902452815158017"
    },
    {
      "rank": 47,
      "score": 11592294,
      "userId": "7233401788634831618"
    },
    {
      "rank": 48,
      "score": 11510893,
      "userId": "7091556119771945729"
    },
    {
      "rank": 49,
      "score": 11179116,
      "userId": "7069817782174800641"
    },
    {
      "rank": 50,
      "score": 11120302,
      "userId": "7046365366540507905"
    },
    {
      "rank": 51,
      "score": 10808833,
      "userId": "7146128914358770433"
    },
    {
      "rank": 52,
      "score": 10540795,
      "userId": "7312987844719434498"
    },
    {
      "rank": 53,
      "score": 10347328,
      "userId": "7133997953202789121"
    },
    {
      "rank": 54,
      "score": 10270302,
      "userId": "7022934685697186562"
    },
    {
      "rank": 55,
      "score": 10162912,
      "userId": "7217070688455301890"
    },
    {
      "rank": 56,
      "score": 10160186,
      "userId": "7066863923932437249"
    },
    {
      "rank": 57,
      "score": 10137961,
      "userId": "7309402995719117570"
    },
    {
      "rank": 58,
      "score": 10135717,
      "userId": "7165896982601571073"
    },
    {
      "rank": 59,
      "score": 10128846,
      "userId": "7273404316487113474"
    },
    {
      "rank": 60,
      "score": 10110624,
      "userId": "7247844792946924290"
    },
    {
      "rank": 61,
      "score": 10062694,
      "userId": "7229571878656989954"
    },
    {
      "rank": 62,
      "score": 10060126,
      "userId": "7026424108665805569"
    },
    {
      "rank": 63,
      "score": 10055173,
      "userId": "7013493176786803458"
    },
    {
      "rank": 64,
      "score": 10019271,
      "userId": "7040915771341462273"
    },
    {
      "rank": 65,
      "score": 10004791,
      "userId": "7015939407953894145"
    },
    {
      "rank": 66,
      "score": 10001112,
      "userId": "7013945005517871873"
    },
    {
      "rank": 67,
      "score": 10000302,
      "userId": "7096795786087815938"
    },
    {
      "rank": 68,
      "score": 10000302,
      "userId": "7025606837865093889"
    },
    {
      "rank": 69,
      "score": 10000302,
      "userId": "7209169761597545217"
    },
    {
      "rank": 70,
      "score": 10000302,
      "userId": "7019713359901842177"
    },
    {
      "rank": 71,
      "score": 9980246,
      "userId": "7301908482859686658"
    },
    {
      "rank": 72,
      "score": 9913323,
      "userId": "7013788944110344961"
    },
    {
      "rank": 73,
      "score": 9888287,
      "userId": "7068636360252349185"
    },
    {
      "rank": 74,
      "score": 9886207,
      "userId": "7003002346502658818"
    },
    {
      "rank": 75,
      "score": 9871992,
      "userId": "7181083799449705218"
    },
    {
      "rank": 76,
      "score": 9826751,
      "userId": "7002439152197393153"
    },
    {
      "rank": 77,
      "score": 9826558,
      "userId": "7258249683485694722"
    },
    {
      "rank": 78,
      "score": 9809109,
      "userId": "7197053474239077122"
    },
    {
      "rank": 79,
      "score": 9809006,
      "userId": "7014028858412243713"
    },
    {
      "rank": 80,
      "score": 9794152,
      "userId": "7329261452131588865"
    },
    {
      "rank": 81,
      "score": 9750905,
      "userId": "7049191463011375873"
    },
    {
      "rank": 82,
      "score": 9750302,
      "userId": "7045190039055112961"
    },
    {
      "rank": 83,
      "score": 9742652,
      "userId": "7002435451118181121"
    },
    {
      "rank": 84,
      "score": 9726555,
      "userId": "7037026450565831425"
    },
    {
      "rank": 85,
      "score": 9724005,
      "userId": "7013651234171198209"
    },
    {
      "rank": 86,
      "score": 9714018,
      "userId": "7168775569830796034"
    },
    {
      "rank": 87,
      "score": 9711112,
      "userId": "7014806831713524482"
    },
    {
      "rank": 88,
      "score": 9700525,
      "userId": "7214817821216283394"
    },
    {
      "rank": 89,
      "score": 9695840,
      "userId": "7224730630716676866"
    },
    {
      "rank": 90,
      "score": 9689337,
      "userId": "7014047780591115009"
    },
    {
      "rank": 91,
      "score": 9674216,
      "userId": "7013874881456560897"
    },
    {
      "rank": 92,
      "score": 9660249,
      "userId": "7103134823556078337"
    },
    {
      "rank": 93,
      "score": 9639852,
      "userId": "7025610233414359810"
    },
    {
      "rank": 94,
      "score": 9639111,
      "userId": "7301674928770865921"
    },
    {
      "rank": 95,
      "score": 9615447,
      "userId": "7013386183002790658"
    },
    {
      "rank": 96,
      "score": 9595778,
      "userId": "7063064618897283842"
    },
    {
      "rank": 97,
      "score": 9549931,
      "userId": "7037845497339599617"
    },
    {
      "rank": 98,
      "score": 9545619,
      "userId": "7315447666757098242"
    },
    {
      "rank": 99,
      "score": 9525677,
      "userId": "7197309912978938626"
    },
    {
      "rank": 100,
      "score": 9333054,
      "userId": "7013749955382745857"
    },
    {
      "rank": 200,
      "score": 4066909,
      "userId": "7080323908339227394"
    },
    {
      "rank": 300,
      "score": 3313250,
      "userId": "7187293195510979330"
    },
    {
      "rank": 400,
      "score": 3037402,
      "userId": "7013623061119343361"
    },
    {
      "rank": 500,
      "score": 2989060,
      "userId": "7025494541729929985"
    },
    {
      "rank": 1000,
      "score": 2288697,
      "userId": "7160641833733823233"
    },
    {
      "rank": 2000,
      "score": 1609160,
      "userId": "7192486575958137601"
    },
    {
      "rank": 3000,
      "score": 1389712,
      "userId": "7024066407595776769"
    },
    {
      "rank": 4000,
      "score": 1262145,
      "userId": "7247506094451579649"
    },
    {
      "rank": 5000,
      "score": 1199100,
      "userId": "7064986587519818497"
    },
    {
      "rank": 10000,
      "score": 753187,
      "userId": "7169994416856472321"
    },
    {
      "rank": 20000,
      "score": 432265,
      "userId": "7333782919208508161"
    },
    {
      "rank": 30000,
      "score": 314445,
      "userId": "7146173028798356226"
    },
    {
      "rank": 40000,
      "score": 243859,
      "userId": "7234830928571374338"
    },
    {
      "rank": 50000,
      "score": 194088,
      "userId": "7037039718265215745"
    },
    {
      "rank": 100000,
      "score": 61855,
      "userId": "7333642001096776449"
    },
    {
      "rank": 200000,
      "score": 3765,
      "userId": "7124172053237766914"
    }
  ]
}